<?xml version="1.0" encoding="UTF-8"?>
<GRAMMAR>
    <NONTERMINALS>
    </NONTERMINALS>
    <TERMINALS>
        <T>
            <ID>CONCATERM_0</ID>
            <PATTERN>"("</PATTERN>
        </T>
        <T>
            <ID>CONCATERM_1</ID>
            <PATTERN>")"</PATTERN>
        </T>
        <T>
            <ID>CONCATERM_2</ID>
            <PATTERN>","</PATTERN>
        </T>
        <T>
            <ID>CONCATERM_3</ID>
            <PATTERN>"a0"</PATTERN>
        </T>
        <T>
            <ID>CONCATERM_4</ID>
            <PATTERN>"a1"</PATTERN>
        </T>
        <T>
            <ID>CONCATERM_5</ID>
            <PATTERN>"a2"</PATTERN>
        </T>
        <T>
            <ID>CONCATERM_6</ID>
            <PATTERN>"a3"</PATTERN>
        </T>
        <T>
            <ID>CONCATERM_7</ID>
            <PATTERN>"a4"</PATTERN>
        </T>
        <T>
            <ID>CONCATERM_8</ID>
            <PATTERN>"a5"</PATTERN>
        </T>
        <T>
            <ID>CONCATERM_9</ID>
            <PATTERN>"a6"</PATTERN>
        </T>
        <T>
            <ID>CONCATERM_10</ID>
            <PATTERN>"a7"</PATTERN>
        </T>
        <T>
            <ID>CONCATERM_11</ID>
            <PATTERN>"add"</PATTERN>
        </T>
        <T>
            <ID>CONCATERM_12</ID>
            <PATTERN>"addi"</PATTERN>
        </T>
        <T>
            <ID>CONCATERM_13</ID>
            <PATTERN>"and"</PATTERN>
        </T>
        <T>
            <ID>CONCATERM_14</ID>
            <PATTERN>"andi"</PATTERN>
        </T>
        <T>
            <ID>CONCATERM_15</ID>
            <PATTERN>"auipc"</PATTERN>
        </T>
        <T>
            <ID>CONCATERM_16</ID>
            <PATTERN>"beq"</PATTERN>
        </T>
        <T>
            <ID>CONCATERM_17</ID>
            <PATTERN>"beqz"</PATTERN>
        </T>
        <T>
            <ID>CONCATERM_18</ID>
            <PATTERN>"bge"</PATTERN>
        </T>
        <T>
            <ID>CONCATERM_19</ID>
            <PATTERN>"bgeu"</PATTERN>
        </T>
        <T>
            <ID>CONCATERM_20</ID>
            <PATTERN>"bgez"</PATTERN>
        </T>
        <T>
            <ID>CONCATERM_21</ID>
            <PATTERN>"bgt"</PATTERN>
        </T>
        <T>
            <ID>CONCATERM_22</ID>
            <PATTERN>"bgtu"</PATTERN>
        </T>
        <T>
            <ID>CONCATERM_23</ID>
            <PATTERN>"bgtz"</PATTERN>
        </T>
        <T>
            <ID>CONCATERM_24</ID>
            <PATTERN>"ble"</PATTERN>
        </T>
        <T>
            <ID>CONCATERM_25</ID>
            <PATTERN>"bleu"</PATTERN>
        </T>
        <T>
            <ID>CONCATERM_26</ID>
            <PATTERN>"blez"</PATTERN>
        </T>
        <T>
            <ID>CONCATERM_27</ID>
            <PATTERN>"blt"</PATTERN>
        </T>
        <T>
            <ID>CONCATERM_28</ID>
            <PATTERN>"bltu"</PATTERN>
        </T>
        <T>
            <ID>CONCATERM_29</ID>
            <PATTERN>"bltz"</PATTERN>
        </T>
        <T>
            <ID>CONCATERM_30</ID>
            <PATTERN>"bne"</PATTERN>
        </T>
        <T>
            <ID>CONCATERM_31</ID>
            <PATTERN>"bnez"</PATTERN>
        </T>
        <T>
            <ID>CONCATERM_32</ID>
            <PATTERN>"call"</PATTERN>
        </T>
        <T>
            <ID>CONCATERM_33</ID>
            <PATTERN>"call_reg"</PATTERN>
        </T>
        <T>
            <ID>CONCATERM_34</ID>
            <PATTERN>"fp"</PATTERN>
        </T>
        <T>
            <ID>CONCATERM_35</ID>
            <PATTERN>"gp"</PATTERN>
        </T>
        <T>
            <ID>CONCATERM_36</ID>
            <PATTERN>"halt"</PATTERN>
        </T>
        <T>
            <ID>CONCATERM_37</ID>
            <PATTERN>"j"</PATTERN>
        </T>
        <T>
            <ID>CONCATERM_38</ID>
            <PATTERN>"jal"</PATTERN>
        </T>
        <T>
            <ID>CONCATERM_39</ID>
            <PATTERN>"jalr"</PATTERN>
        </T>
        <T>
            <ID>CONCATERM_40</ID>
            <PATTERN>"jr"</PATTERN>
        </T>
        <T>
            <ID>CONCATERM_41</ID>
            <PATTERN>"lb"</PATTERN>
        </T>
        <T>
            <ID>CONCATERM_42</ID>
            <PATTERN>"lbu"</PATTERN>
        </T>
        <T>
            <ID>CONCATERM_43</ID>
            <PATTERN>"lh"</PATTERN>
        </T>
        <T>
            <ID>CONCATERM_44</ID>
            <PATTERN>"lhu"</PATTERN>
        </T>
        <T>
            <ID>CONCATERM_45</ID>
            <PATTERN>"li"</PATTERN>
        </T>
        <T>
            <ID>CONCATERM_46</ID>
            <PATTERN>"lui"</PATTERN>
        </T>
        <T>
            <ID>CONCATERM_47</ID>
            <PATTERN>"lw"</PATTERN>
        </T>
        <T>
            <ID>CONCATERM_48</ID>
            <PATTERN>"mv"</PATTERN>
        </T>
        <T>
            <ID>CONCATERM_49</ID>
            <PATTERN>"neg"</PATTERN>
        </T>
        <T>
            <ID>CONCATERM_50</ID>
            <PATTERN>"nop"</PATTERN>
        </T>
        <T>
            <ID>CONCATERM_51</ID>
            <PATTERN>"not"</PATTERN>
        </T>
        <T>
            <ID>CONCATERM_52</ID>
            <PATTERN>"or"</PATTERN>
        </T>
        <T>
            <ID>CONCATERM_53</ID>
            <PATTERN>"ori"</PATTERN>
        </T>
        <T>
            <ID>CONCATERM_54</ID>
            <PATTERN>"ra"</PATTERN>
        </T>
        <T>
            <ID>CONCATERM_55</ID>
            <PATTERN>"ret"</PATTERN>
        </T>
        <T>
            <ID>CONCATERM_56</ID>
            <PATTERN>"s0"</PATTERN>
        </T>
        <T>
            <ID>CONCATERM_57</ID>
            <PATTERN>"s1"</PATTERN>
        </T>
        <T>
            <ID>CONCATERM_58</ID>
            <PATTERN>"s10"</PATTERN>
        </T>
        <T>
            <ID>CONCATERM_59</ID>
            <PATTERN>"s11"</PATTERN>
        </T>
        <T>
            <ID>CONCATERM_60</ID>
            <PATTERN>"s2"</PATTERN>
        </T>
        <T>
            <ID>CONCATERM_61</ID>
            <PATTERN>"s3"</PATTERN>
        </T>
        <T>
            <ID>CONCATERM_62</ID>
            <PATTERN>"s4"</PATTERN>
        </T>
        <T>
            <ID>CONCATERM_63</ID>
            <PATTERN>"s5"</PATTERN>
        </T>
        <T>
            <ID>CONCATERM_64</ID>
            <PATTERN>"s6"</PATTERN>
        </T>
        <T>
            <ID>CONCATERM_65</ID>
            <PATTERN>"s7"</PATTERN>
        </T>
        <T>
            <ID>CONCATERM_66</ID>
            <PATTERN>"s8"</PATTERN>
        </T>
        <T>
            <ID>CONCATERM_67</ID>
            <PATTERN>"s9"</PATTERN>
        </T>
        <T>
            <ID>CONCATERM_68</ID>
            <PATTERN>"sb"</PATTERN>
        </T>
        <T>
            <ID>CONCATERM_69</ID>
            <PATTERN>"seqz"</PATTERN>
        </T>
        <T>
            <ID>CONCATERM_70</ID>
            <PATTERN>"sgt"</PATTERN>
        </T>
        <T>
            <ID>CONCATERM_71</ID>
            <PATTERN>"sgtz"</PATTERN>
        </T>
        <T>
            <ID>CONCATERM_72</ID>
            <PATTERN>"sh"</PATTERN>
        </T>
        <T>
            <ID>CONCATERM_73</ID>
            <PATTERN>"sll"</PATTERN>
        </T>
        <T>
            <ID>CONCATERM_74</ID>
            <PATTERN>"slli"</PATTERN>
        </T>
        <T>
            <ID>CONCATERM_75</ID>
            <PATTERN>"slt"</PATTERN>
        </T>
        <T>
            <ID>CONCATERM_76</ID>
            <PATTERN>"slti"</PATTERN>
        </T>
        <T>
            <ID>CONCATERM_77</ID>
            <PATTERN>"sltiu"</PATTERN>
        </T>
        <T>
            <ID>CONCATERM_78</ID>
            <PATTERN>"sltu"</PATTERN>
        </T>
        <T>
            <ID>CONCATERM_79</ID>
            <PATTERN>"sltz"</PATTERN>
        </T>
        <T>
            <ID>CONCATERM_80</ID>
            <PATTERN>"snez"</PATTERN>
        </T>
        <T>
            <ID>CONCATERM_81</ID>
            <PATTERN>"sp"</PATTERN>
        </T>
        <T>
            <ID>CONCATERM_82</ID>
            <PATTERN>"sra"</PATTERN>
        </T>
        <T>
            <ID>CONCATERM_83</ID>
            <PATTERN>"srai"</PATTERN>
        </T>
        <T>
            <ID>CONCATERM_84</ID>
            <PATTERN>"srl"</PATTERN>
        </T>
        <T>
            <ID>CONCATERM_85</ID>
            <PATTERN>"srli"</PATTERN>
        </T>
        <T>
            <ID>CONCATERM_86</ID>
            <PATTERN>"sub"</PATTERN>
        </T>
        <T>
            <ID>CONCATERM_87</ID>
            <PATTERN>"sw"</PATTERN>
        </T>
        <T>
            <ID>CONCATERM_88</ID>
            <PATTERN>"t0"</PATTERN>
        </T>
        <T>
            <ID>CONCATERM_89</ID>
            <PATTERN>"t1"</PATTERN>
        </T>
        <T>
            <ID>CONCATERM_90</ID>
            <PATTERN>"t2"</PATTERN>
        </T>
        <T>
            <ID>CONCATERM_91</ID>
            <PATTERN>"t3"</PATTERN>
        </T>
        <T>
            <ID>CONCATERM_92</ID>
            <PATTERN>"t4"</PATTERN>
        </T>
        <T>
            <ID>CONCATERM_93</ID>
            <PATTERN>"t5"</PATTERN>
        </T>
        <T>
            <ID>CONCATERM_94</ID>
            <PATTERN>"t6"</PATTERN>
        </T>
        <T>
            <ID>CONCATERM_95</ID>
            <PATTERN>"tp"</PATTERN>
        </T>
        <T>
            <ID>CONCATERM_96</ID>
            <PATTERN>"x0"</PATTERN>
        </T>
        <T>
            <ID>CONCATERM_97</ID>
            <PATTERN>"x1"</PATTERN>
        </T>
        <T>
            <ID>CONCATERM_98</ID>
            <PATTERN>"x10"</PATTERN>
        </T>
        <T>
            <ID>CONCATERM_99</ID>
            <PATTERN>"x11"</PATTERN>
        </T>
        <T>
            <ID>CONCATERM_100</ID>
            <PATTERN>"x12"</PATTERN>
        </T>
        <T>
            <ID>CONCATERM_101</ID>
            <PATTERN>"x13"</PATTERN>
        </T>
        <T>
            <ID>CONCATERM_102</ID>
            <PATTERN>"x14"</PATTERN>
        </T>
        <T>
            <ID>CONCATERM_103</ID>
            <PATTERN>"x15"</PATTERN>
        </T>
        <T>
            <ID>CONCATERM_104</ID>
            <PATTERN>"x16"</PATTERN>
        </T>
        <T>
            <ID>CONCATERM_105</ID>
            <PATTERN>"x17"</PATTERN>
        </T>
        <T>
            <ID>CONCATERM_106</ID>
            <PATTERN>"x18"</PATTERN>
        </T>
        <T>
            <ID>CONCATERM_107</ID>
            <PATTERN>"x19"</PATTERN>
        </T>
        <T>
            <ID>CONCATERM_108</ID>
            <PATTERN>"x2"</PATTERN>
        </T>
        <T>
            <ID>CONCATERM_109</ID>
            <PATTERN>"x20"</PATTERN>
        </T>
        <T>
            <ID>CONCATERM_110</ID>
            <PATTERN>"x21"</PATTERN>
        </T>
        <T>
            <ID>CONCATERM_111</ID>
            <PATTERN>"x22"</PATTERN>
        </T>
        <T>
            <ID>CONCATERM_112</ID>
            <PATTERN>"x23"</PATTERN>
        </T>
        <T>
            <ID>CONCATERM_113</ID>
            <PATTERN>"x24"</PATTERN>
        </T>
        <T>
            <ID>CONCATERM_114</ID>
            <PATTERN>"x25"</PATTERN>
        </T>
        <T>
            <ID>CONCATERM_115</ID>
            <PATTERN>"x26"</PATTERN>
        </T>
        <T>
            <ID>CONCATERM_116</ID>
            <PATTERN>"x27"</PATTERN>
        </T>
        <T>
            <ID>CONCATERM_117</ID>
            <PATTERN>"x28"</PATTERN>
        </T>
        <T>
            <ID>CONCATERM_118</ID>
            <PATTERN>"x29"</PATTERN>
        </T>
        <T>
            <ID>CONCATERM_119</ID>
            <PATTERN>"x3"</PATTERN>
        </T>
        <T>
            <ID>CONCATERM_120</ID>
            <PATTERN>"x30"</PATTERN>
        </T>
        <T>
            <ID>CONCATERM_121</ID>
            <PATTERN>"x31"</PATTERN>
        </T>
        <T>
            <ID>CONCATERM_122</ID>
            <PATTERN>"x4"</PATTERN>
        </T>
        <T>
            <ID>CONCATERM_123</ID>
            <PATTERN>"x5"</PATTERN>
        </T>
        <T>
            <ID>CONCATERM_124</ID>
            <PATTERN>"x6"</PATTERN>
        </T>
        <T>
            <ID>CONCATERM_125</ID>
            <PATTERN>"x7"</PATTERN>
        </T>
        <T>
            <ID>CONCATERM_126</ID>
            <PATTERN>"x8"</PATTERN>
        </T>
        <T>
            <ID>CONCATERM_127</ID>
            <PATTERN>"x9"</PATTERN>
        </T>
        <T>
            <ID>CONCATERM_128</ID>
            <PATTERN>"xor"</PATTERN>
        </T>
        <T>
            <ID>CONCATERM_129</ID>
            <PATTERN>"xori"</PATTERN>
        </T>
        <T>
            <ID>CONCATERM_130</ID>
            <PATTERN>"zero"</PATTERN>
        </T>
    </TERMINALS>
    <RULES>
    </RULES>
</GRAMMAR>
